pygame_starter/__init__.py
pygame_starter/gerador.py
pygame_starter-0.3.7.dist-info/METADATA
pygame_starter-0.3.7.dist-info/WHEEL
pygame_starter-0.3.7.dist-info/entry_points.txt
pygame_starter-0.3.7.dist-info/top_level.txt
pygame_starter-0.3.7.dist-info/RECORD
