Metadata-Version: 2.4
Name: pygame_starter
Version: 0.3.7
Summary: Gerador automático de projetos base em Pygame com menu, resolução, cor e recorde
Author: Seu Nome
Requires-Python: >=3.6
Dynamic: author
Dynamic: description
Dynamic: description-content-type
Dynamic: requires-python
Dynamic: summary
